ninetoothed/__init__.py
ninetoothed/aot.py
ninetoothed/cudaifier.py
ninetoothed/debugging.py
ninetoothed/dtype.py
ninetoothed/eval.py
ninetoothed/generation.py
ninetoothed/jit.py
ninetoothed/language.py
ninetoothed/make.py
ninetoothed/naming.py
ninetoothed/symbol.py
ninetoothed/tensor.py
ninetoothed/torchifier.py
ninetoothed/utils.py
ninetoothed/visualization.py
ninetoothed-0.21.0.dist-info/METADATA
ninetoothed-0.21.0.dist-info/WHEEL
ninetoothed-0.21.0.dist-info/licenses/LICENSE
ninetoothed-0.21.0.dist-info/RECORD
