Metadata-Version: 2.4
Name: ninetoothed
Version: 0.21.0
Summary: A domain-specific language based on Triton but providing higher-level abstraction.
Project-URL: Homepage, https://github.com/InfiniTensor/ninetoothed
Project-URL: Issues, https://github.com/InfiniTensor/ninetoothed/issues
Author-email: Jiacheng Huang <huangjiacheng0709@outlook.com>
License-File: LICENSE
Classifier: License :: OSI Approved :: Apache Software License
Classifier: Operating System :: OS Independent
Classifier: Programming Language :: Python :: 3
Requires-Python: >=3.10
Requires-Dist: numpy>=2.1.0
Requires-Dist: sympy>=1.13.0
Requires-Dist: triton>=3.0.0
Provides-Extra: all
Requires-Dist: matplotlib>=3.9.0; extra == 'all'
Requires-Dist: torch>=2.4.0; extra == 'all'
Provides-Extra: debugging
Requires-Dist: torch>=2.4.0; extra == 'debugging'
Provides-Extra: visualization
Requires-Dist: matplotlib>=3.9.0; extra == 'visualization'
Requires-Dist: torch>=2.4.0; extra == 'visualization'
